coolbot/__init__.py
coolbot/bot.py
coolbot/embeds.py
coolbot_framework-0.1.0.dist-info/licenses/LICENSE
coolbot_framework-0.1.0.dist-info/METADATA
coolbot_framework-0.1.0.dist-info/WHEEL
coolbot_framework-0.1.0.dist-info/top_level.txt
coolbot_framework-0.1.0.dist-info/RECORD
