Metadata-Version: 2.4
Name: coolbot-framework
Version: 0.1.0
Summary: A cool and easy wrapper for Disnake to build Discord bots faster.
Author-email: "xPRINCE >> LK-TEAM" <unknown@gmail.com>
Project-URL: Homepage, https://unknownbroohahahah
Classifier: Programming Language :: Python :: 3
Classifier: License :: OSI Approved :: MIT License
Classifier: Operating System :: OS Independent
Classifier: Topic :: Software Development :: Libraries :: Python Modules
Requires-Python: >=3.8
License-File: LICENSE
Requires-Dist: disnake>=2.8.0
Dynamic: license-file
